[
  {
	"name": "every_possible_country",
	"specificScopes": ["ALL"],
	"targetType": "COUNTRY"
  },
  {
	"name": "every_country",
	"specificScopes": ["ALL"],
	"targetType": "COUNTRY"
  },
  {
	"name": "random_country",
	"specificScopes": ["ALL"],
	"targetType": "COUNTRY"
  },
  {
	"name": "every_other_country",
	"specificScopes": ["COUNTRY"],
	"targetType": "COUNTRY"
  },
  {
	"name": "random_other_country",
	"specificScopes": ["COUNTRY"],
	"targetType": "COUNTRY"
  },
  {
	"name": "every_country_with_original_tag",
	"specificScopes": ["ALL"],
	"targetType": "COUNTRY",
	"mandatoryInnerBlocks": {
		"original_tag_to_check": {
			"name": "original_tag_to_check",
			"allowedValueTypes": ["COUNTRY"]
		}
	}
  },
  {
	"name": "random_country_with_original_tag",
	"specificScopes": ["ALL"],
	"targetType": "COUNTRY",
	"mandatoryInnerBlocks": {
		"original_tag_to_check": {
			"name": "original_tag_to_check",
			"allowedValueTypes": ["COUNTRY"]
		}
	}
  },
  {
	"name": "every_neighbor_country",
	"specificScopes": ["COUNTRY"],
	"targetType": "COUNTRY"
  },
  {
	"name": "random_neighbor_country",
	"specificScopes": ["COUNTRY"],
	"targetType": "COUNTRY"
  },
  {
	"name": "every_occupied_country",
	"specificScopes": ["COUNTRY"],
	"targetType": "COUNTRY"
  },
  {
	"name": "random_occupied_country",
	"specificScopes": ["COUNTRY"],
	"targetType": "COUNTRY"
  },
  {
	"name": "every_enemy_country",
	"specificScopes": ["COUNTRY"],
	"targetType": "COUNTRY"
  },
  {
	"name": "random_enemy_country",
	"specificScopes": ["COUNTRY"],
	"targetType": "COUNTRY"
  },
  {
	"name": "every_subject_country",
	"specificScopes": ["COUNTRY"],
	"targetType": "COUNTRY"
  },
  {
	"name": "random_subject_country",
	"specificScopes": ["COUNTRY"],
	"targetType": "COUNTRY"
  },
  {
	"name": "every_state",
	"specificScopes": ["ALL"],
	"targetType": "STATE"
  },
  {
	"name": "random_state",
	"specificScopes": ["ALL"],
	"targetType": "STATE",
	"optionalInnerBlocks": {
		"prioritize": {
			"name": "prioritize",
			"allowedValueTypes": ["STATE"]
		}
	}
  },
  {
	"name": "every_neighbor_state",
	"specificScopes": ["STATE"],
	"targetType": "STATE"
  },
  {
	"name": "random_neighbor_state",
	"specificScopes": ["STATE"],
	"targetType": "STATE"
  },
  {
	"name": "every_owned_state",
	"specificScopes": ["COUNTRY"],
	"targetType": "STATE"
  },
  {
	"name": "random_owned_state",
	"specificScopes": ["COUNTRY"],
	"targetType": "STATE",
	"optionalInnerBlocks": {
		"prioritize": {
			"name": "prioritize",
			"allowedValueTypes": ["STATE"]
		}
	}
  },
  {
	"name": "every_core_state",
	"specificScopes": ["COUNTRY"],
	"targetType": "STATE"
  },
  {
	"name": "random_core_state",
	"specificScopes": ["COUNTRY"],
	"targetType": "STATE",
	"optionalInnerBlocks": {
		"prioritize": {
			"name": "prioritize",
			"allowedValueTypes": ["STATE"]
		}
	}
  },
  {
	"name": "every_controlled_state",
	"specificScopes": ["COUNTRY"],
	"targetType": "STATE"
  },
  {
	"name": "random_controlled_state",
	"specificScopes": ["COUNTRY"],
	"targetType": "STATE",
	"optionalInnerBlocks": {
		"prioritize": {
			"name": "prioritize",
			"allowedValueTypes": ["STATE"]
		}
	}
  },
  {
	"name": "random_owned_controlled_state",
	"specificScopes": ["COUNTRY"],
	"targetType": "STATE",
	"optionalInnerBlocks": {
		"prioritize": {
			"name": "prioritize",
			"allowedValueTypes": ["STATE"]
		}
	}
  },
  {
	"name": "every_unit_leader",
	"specificScopes": ["COUNTRY"],
	"targetType": "UNIT_LEADER"
  },
  {
	"name": "random_unit_leader",
	"specificScopes": ["COUNTRY"],
	"targetType": "UNIT_LEADER"
  },
  {
	"name": "every_army_leader",
	"specificScopes": ["COUNTRY"],
	"targetType": "UNIT_LEADER"
  },
  {
	"name": "random_army_leader",
	"specificScopes": ["COUNTRY"],
	"targetType": "UNIT_LEADER"
  },
  {
	"name": "global_every_army_leader",
	"specificScopes": ["COUNTRY"],
	"targetType": "UNIT_LEADER"
  },
  {
	"name": "every_navy_leader",
	"specificScopes": ["COUNTRY"],
	"targetType": "UNIT_LEADER"
  },
  {
	"name": "random_navy_leader",
	"specificScopes": ["COUNTRY"],
	"targetType": "UNIT_LEADER"
  },
  {
	"name": "every_operative",
	"specificScopes": ["COUNTRY"],
	"targetType": "OPERATIVE"
  },
  {
	"name": "random_operative",
	"specificScopes": ["COUNTRY"],
	"targetType": "UNIT_LEADER"
  },
  {
	"name": "every_character",
	"specificScopes": ["COUNTRY"],
	"targetType": "CHARACTER"
  },
  {
	"name": "random_character",
	"specificScopes": ["COUNTRY"],
	"targetType": "CHARACTER"
  },
  {
	"name": "every_country_division",
	"specificScopes": ["COUNTRY"],
	"targetType": "DIVISION"
  },
  {
	"name": "random_country_division",
	"specificScopes": ["COUNTRY"],
	"targetType": "DIVISION"
  },
  {
	"name": "every_state_division",
	"specificScopes": ["COUNTRY"],
	"targetType": "DIVISION"
  },
  {
	"name": "random_state_division",
	"specificScopes": ["COUNTRY"],
	"targetType": "DIVISION"
  },
  {
	"name": "every_military_industrial_organization",
	"specificScopes": ["COUNTRY"],
	"targetType": "MIO"
  },
  {
	"name": "random_military_industrial_organization",
	"specificScopes": ["COUNTRY"],
	"targetType": "MIO"
  },
  {
	"name": "every_purchase_contract",
	"specificScopes": ["COUNTRY"],
	"targetType": "PURCHASE_CONTRACT"
  },
  {
	"name": "random_purchase_contract",
	"specificScopes": ["COUNTRY"],
	"targetType": "PURCHASE_CONTRACT"
  },
  {
	"name": "party_leader",
	"specificScopes": ["COUNTRY"],
	"targetType": "CHARACTER",
	"mandatoryInnerBlocks": {
		"limit": {
			"name": "limit",
			"mandatoryInnerBlocks": {
				"has_ideology": {
					"name": "has_ideology",
					"allowedValueTypes": ["IDEOLOGY"]
				}
			}
		}
	}
  },
  
  
  
  {
	"name": "always",
	"specificScopes": ["ALL"],
    "allowedValueTypes": ["BOOLEAN"]
  },
  {
    "name": "has_global_flag",
	"specificScopes": ["ALL"],
	"mandatoryInnerBlocks": {
		"flag": {
			"name": "flag",
			"allowedValueTypes": ["STRING"]
		}
	},
	"allowedInnerBlocks": {
		"days": {
			"name": "days",
			"allowedValueTypes": ["INT"],
			"allowedSpecialDemiliters": ["EQUALS", "LESS_THAN", "GREATER_THAN"]
		},
		"date": {
			"name": "date",
			"allowedValueTypes": ["STRING"],
			"allowedSpecialDemiliters": ["EQUALS", "LESS_THAN", "GREATER_THAN"]
		},
		"value": {
			"name": "value",
			"allowedValueTypes": ["INT"],
			"allowedSpecialDemiliters": ["EQUALS", "LESS_THAN", "GREATER_THAN"]
		}
	},
    "allowedValueTypes": ["STRING"]
  },
  {
	"name": "has_dlc",
	"specificScopes": ["ALL"],
    "allowedValueTypes": ["STRING"]
  },
  {
	"name": "has_start_date",
	"specificScopes": ["ALL"],
    "allowedValueTypes": ["STRING"],
	"allowedSpecialDemiliters": ["LESS_THAN", "GREATER_THAN"]
  },
  {
	"name": "date",
	"specificScopes": ["ALL"],
    "allowedValueTypes": ["STRING"],
	"allowedSpecialDemiliters": ["LESS_THAN", "GREATER_THAN"]
  },
  {
	"name": "difficulty",
	"specificScopes": ["ALL"],
    "allowedValueTypes": ["INT"],
	"allowedSpecialDemiliters": ["LESS_THAN", "GREATER_THAN"]
  },
  {
	"name": "has_any_custom_difficulty_setting",
	"specificScopes": ["ALL"],
    "allowedValueTypes": ["BOOLEAN"]
  },
  {
	"name": "has_custom_difficulty_setting",
	"specificScopes": ["ALL"],
    "allowedValueTypes": ["STRING"]
  },
  {
	"name": "game_rules_allow_achievements",
	"specificScopes": ["ALL"],
    "allowedValueTypes": ["BOOLEAN"]
  },
  {
	"name": "country_exists",
	"specificScopes": ["ALL"],
    "allowedValueTypes": ["VAR", "SCOPE"]
  },
  {
	"name": "is_ironman",
	"specificScopes": ["ALL"],
    "allowedValueTypes": ["BOOLEAN"]
  },
  {
	"name": "is_historical_focus_on",
	"specificScopes": ["ALL"],
    "allowedValueTypes": ["BOOLEAN"]
  },
  {
	"name": "is_tutorial",
	"specificScopes": ["ALL"],
    "allowedValueTypes": ["BOOLEAN"]
  },
  {
	"name": "is_debug",
	"specificScopes": ["ALL"],
    "allowedValueTypes": ["BOOLEAN"]
  },
  {
	"name": "threat",
	"specificScopes": ["ALL"],
    "allowedValueTypes": ["FLOAT"],
	"allowedSpecialDemiliters": ["LESS_THAN", "GREATER_THAN"]
  },
  {
	"name": "has_game_rule",
	"specificScopes": ["ALL"],
	"mandatoryInnerBlocks": {
		"rule": {
			"name": "rule",
			"allowedValueTypes": ["STRING"]
		}
	},
	"allowedUniversalParamsInfo": {
		"maxUniversalParamsCount": 1,
		"ignoreMandatoryInnerBlocksCheck": false,
		"canBeMixedWithOutherTypeBlocks": true,
		"allowedValueTypes": ["FLOAT"],
		"allowedSpecialDemiliters": ["LESS_THAN", "GREATER_THAN"]
	}
  },
  
  {
	"name": "check_variable",
	"specificScopes": ["ALL"],
	"mandatoryInnerBlocks": {
		"var": {
			"name": "var",
			"allowedValueTypes": ["VAR"]
		},
		"value": {
			"name": "value",
			"allowedValueTypes": ["VAR", "FLOAT"]
		},
		"compare": {
			"name": "compare",
			"allowedValueTypes": ["STRING"]
		}
	},
	"allowedUniversalParamsInfo": {
		"maxUniversalParamsCount": 1,
		"ignoreMandatoryInnerBlocksCheck": true,
		"canBeMixedWithOutherTypeBlocks": true,
		"allowedValueTypes": ["VAR", "FLOAT"],
		"allowedSpecialDemiliters": ["LESS_THAN", "GREATER_THAN"]
	}
  },
  {
	"name": "check_temp_variable",
	"specificScopes": ["ALL"],
	"mandatoryInnerBlocks": {
		"var": {
			"name": "var",
			"allowedValueTypes": ["VAR"]
		},
		"value": {
			"name": "value",
			"allowedValueTypes": ["VAR", "FLOAT"]
		},
		"compare": {
			"name": "compare",
			"allowedValueTypes": ["STRING"]
		}
	},
	"allowedUniversalParamsInfo": {
		"maxUniversalParamsCount": 1,
		"ignoreMandatoryInnerBlocksCheck": true,
		"canBeMixedWithOutherTypeBlocks": true,
		"allowedValueTypes": ["VAR", "FLOAT"],
		"allowedSpecialDemiliters": ["LESS_THAN", "GREATER_THAN"]
	}
  },
  {
	"name": "has_variable",
	"specificScopes": ["ALL"],
    "allowedValueTypes": ["VAR"]
  },
  
  
  
  {
	"name": "exists",
	"specificScopes": ["COUNTRY"],
    "allowedValueTypes": ["BOOLEAN"]
  },
  {
	"name": "tag",
	"specificScopes": ["COUNTRY"],
    "allowedValueTypes": ["VAR", "SCOPE"]
  },
  {
	"name": "original_tag",
	"specificScopes": ["COUNTRY"],
    "allowedValueTypes": ["VAR", "SCOPE"]
  },
  {
	"name": "has_collaboration",
	"specificScopes": ["COUNTRY"],
	"mandatoryInnerBlocks": {
		"target": {
			"name": "target",
			"allowedValueTypes": ["COUNTRY"]
		},
		"value": {
			"name": "value",
			"allowedValueTypes": ["DECIMAL"]
		}
	}
  },
  {
    "name": "has_country_flag",
	"specificScopes": ["COUNTRY"],
	"mandatoryInnerBlocks": {
		"flag": {
			"name": "flag",
			"allowedValueTypes": ["STRING"]
		}
	},
	"allowedInnerBlocks": {
		"days": {
			"name": "days",
			"allowedValueTypes": ["INT"],
			"allowedSpecialDemiliters": ["LESS_THAN", "GREATER_THAN"]
		},
		"date": {
			"name": "date",
			"allowedValueTypes": ["STRING"],
			"allowedSpecialDemiliters": ["LESS_THAN", "GREATER_THAN"]
		},
		"value": {
			"name": "value",
			"allowedValueTypes": ["INT"],
			"allowedSpecialDemiliters": ["LESS_THAN", "GREATER_THAN"]
		}
	},
    "allowedValueTypes": ["STRING"]
  },
  
  
  
  {
	"name": "is_major",
	"specificScopes": ["COUNTRY"],
    "allowedValueTypes": ["BOOLEAN"]
  },
  {
	"name": "is_ally_with",
	"specificScopes": ["COUNTRY"],
    "allowedValueTypes": ["VAR", "SCOPE"]
  },
  {
	"name": "is_in_faction_with",
	"specificScopes": ["COUNTRY"],
    "allowedValueTypes": ["VAR", "SCOPE"]
  },
  {
	"name": "is_in_faction",
	"specificScopes": ["COUNTRY"],
    "allowedValueTypes": ["BOOLEAN"]
  },
  {
	"name": "is_faction_leader",
	"specificScopes": ["COUNTRY"],
    "allowedValueTypes": ["BOOLEAN"]
  },
  {
	"name": "is_spymaster",
	"specificScopes": ["COUNTRY"],
    "allowedValueTypes": ["BOOLEAN"]
  },
  {
	"name": "num_faction_members",
	"isDisabled": true,
	"specificScopes": ["COUNTRY"],
    "allowedValueTypes": ["BOOLEAN"]
  },
  {
	"name": "has_non_aggression_pact_with",
	"specificScopes": ["COUNTRY"],
    "allowedValueTypes": ["VAR", "SCOPE"]
  },
  {
	"name": "is_guaranteed_by",
	"specificScopes": ["COUNTRY"],
    "allowedValueTypes": ["VAR", "SCOPE"]
  },
  {
	"name": "has_guaranteed",
	"specificScopes": ["COUNTRY"],
    "allowedValueTypes": ["VAR", "SCOPE"]
  },
  {
	"name": "has_military_access_to",
	"specificScopes": ["COUNTRY"],
    "allowedValueTypes": ["VAR", "SCOPE"]
  },
  {
	"name": "gives_military_access_to",
	"specificScopes": ["COUNTRY"],
    "allowedValueTypes": ["VAR", "SCOPE"]
  },
  {
	"name": "is_neighbor_of",
	"specificScopes": ["COUNTRY"],
    "allowedValueTypes": ["VAR", "SCOPE"]
  },
  {
	"name": "is_owner_neighbor_of",
	"specificScopes": ["COUNTRY"],
    "allowedValueTypes": ["VAR", "SCOPE"]
  },
  {
	"name": "is_puppet_of",
	"specificScopes": ["COUNTRY"],
    "allowedValueTypes": ["VAR", "SCOPE"]
  },
  {
	"name": "is_subject_of",
	"specificScopes": ["COUNTRY"],
    "allowedValueTypes": ["VAR", "SCOPE"]
  },
  {
	"name": "is_puppet",
	"specificScopes": ["COUNTRY"],
    "allowedValueTypes": ["BOOLEAN"]
  },
  {
	"name": "is_subject",
	"specificScopes": ["COUNTRY"],
    "allowedValueTypes": ["BOOLEAN"]
  },
  {
	"name": "has_subject",
	"specificScopes": ["COUNTRY"],
    "allowedValueTypes": ["VAR", "SCOPE"]
  },
  {
	"name": "num_subjects",
	"isDisabled": true,
	"specificScopes": ["COUNTRY"],
    "allowedValueTypes": ["VAR", "SCOPE"]
  },
  {
	"name": "has_autonomy_state",
	"specificScopes": ["COUNTRY"],
    "allowedValueTypes": ["SCOPE"]
  },
  
  
  
  {
	"name": "has_war",
	"specificScopes": ["COUNTRY"],
    "allowedValueTypes": ["BOOLEAN"]
  },
  {
	"name": "has_war_with",
	"specificScopes": ["COUNTRY"],
    "allowedValueTypes": ["VAR", "SCOPE"]
  },
  {
	"name": "has_offensive_war_with",
	"specificScopes": ["COUNTRY"],
    "allowedValueTypes": ["VAR", "SCOPE"]
  },
  {
	"name": "has_defensive_war_with",
	"specificScopes": ["COUNTRY"],
    "allowedValueTypes": ["VAR", "SCOPE"]
  },
  
  
  
  {
	"name": "controls_state",
	"specificScopes": ["COUNTRY"],
    "allowedValueTypes": ["VAR", "INT"]
  },
  {
	"name": "owns_state",
	"specificScopes": ["COUNTRY"],
    "allowedValueTypes": ["VAR", "INT"]
  }
]